LICENSE
README.md
pyproject.toml
setup.py
gpt_trim/__init__.py
gpt_trim/core.py
gpt_trim.egg-info/PKG-INFO
gpt_trim.egg-info/SOURCES.txt
gpt_trim.egg-info/dependency_links.txt
gpt_trim.egg-info/requires.txt
gpt_trim.egg-info/top_level.txt