Metadata-Version: 2.1
Name: gpt-trim
Version: 0.1
Summary: Trims the messages array for ChatGPT API
Author-email: AWeirdDev <aweirdscratcher@gmail.com>
License: MIT License
Project-URL: Homepage, https://github.com/AWeirdScratcher/gpt-trim
Project-URL: Bug Tracker, https://github.com/AWeirdScratcher/gpt-trim/issues
Keywords: gpt,trim,gpt-trim,chatgpt,token,tiktoken
Classifier: Programming Language :: Python :: 3
Classifier: License :: OSI Approved :: MIT License
Classifier: Operating System :: OS Independent
Requires-Python: >=3
License-File: LICENSE
